newswatch/MANIFEST.in
newswatch/__init__.py
newswatch/api.py
newswatch/cli.py
newswatch/exceptions.py
newswatch/main.py
newswatch/models.py
newswatch/utils.py
newswatch/scrapers/__init__.py
newswatch/scrapers/antaranews.py
newswatch/scrapers/basescraper.py
newswatch/scrapers/bisnis.py
newswatch/scrapers/bloombergtechnoz.py
newswatch/scrapers/cnbcindonesia.py
newswatch/scrapers/cnnindonesia.py
newswatch/scrapers/detik.py
newswatch/scrapers/jawapos.py
newswatch/scrapers/katadata.py
newswatch/scrapers/kompas.py
newswatch/scrapers/kontan.py
newswatch/scrapers/liputan6.py
newswatch/scrapers/mediaindonesia.py
newswatch/scrapers/metrotvnews.py
newswatch/scrapers/okezone.py
newswatch/scrapers/tempo.py
newswatch/scrapers/tribunnews.py
newswatch/scrapers/viva.py
news_watch-0.5.0.dist-info/METADATA
news_watch-0.5.0.dist-info/WHEEL
news_watch-0.5.0.dist-info/entry_points.txt
news_watch-0.5.0.dist-info/licenses/LICENSE
news_watch-0.5.0.dist-info/RECORD
