Metadata-Version: 2.4
Name: news-watch
Version: 0.5.0
Summary: news-watch is a Python package that scrapes structured news data from Indonesia's top news websites, offering keyword and date filtering queries for targeted research.
Project-URL: Homepage, https://github.com/okkymabruri/news-watch
Project-URL: Repository, https://github.com/okkymabruri/news-watch.git
Project-URL: Issues, https://github.com/okkymabruri/news-watch/issues
Project-URL: Documentation, https://github.com/okkymabruri/news-watch/tree/main/docs
Project-URL: Changelog, https://github.com/okkymabruri/news-watch/blob/main/docs/changelog.md
Author-email: Okky Mabruri <okkymbrur@gmail.com>
License: MIT
License-File: LICENSE
Keywords: async,data-collection,indonesia,news,scraper,web-scraping
Classifier: Development Status :: 4 - Beta
Classifier: Intended Audience :: Developers
Classifier: Intended Audience :: Science/Research
Classifier: License :: OSI Approved :: MIT License
Classifier: Operating System :: OS Independent
Classifier: Programming Language :: Python :: 3
Classifier: Programming Language :: Python :: 3.10
Classifier: Programming Language :: Python :: 3.11
Classifier: Programming Language :: Python :: 3.12
Classifier: Topic :: Internet :: WWW/HTTP
Classifier: Topic :: Software Development :: Libraries :: Python Modules
Requires-Python: >=3.10
Requires-Dist: aiohttp==3.13.3
Requires-Dist: beautifulsoup4==4.13.4
Requires-Dist: cloudscraper>=1.2.71
Requires-Dist: dateparser==1.2.1
Requires-Dist: openpyxl==3.1.5
Requires-Dist: pandas==2.2.2
Requires-Dist: playwright==1.42.0
Requires-Dist: requests==2.32.4
Provides-Extra: dev
Requires-Dist: pytest-asyncio==0.24.0; extra == 'dev'
Requires-Dist: pytest-timeout==2.3.1; extra == 'dev'
Requires-Dist: pytest==8.3.3; extra == 'dev'
